examples/__init__.py
examples/portfolio.py
tenbagger/__init__.py
tenbagger/cli.py
tenbagger/version.py
tenbagger/configs/__init__.py
tenbagger/configs/environment.json
tenbagger/configs/portfolio.json
tenbagger/configs/staking.json
tenbagger/src/__init__.py
tenbagger/src/configuration/__init__.py
tenbagger/src/configuration/configuration.py
tenbagger/src/crypto/__init__.py
tenbagger/src/crypto/algorand.py
tenbagger/src/crypto/blockchains.py
tenbagger/src/dashboard/__init__.py
tenbagger/src/dashboard/trackerdash.py
tenbagger/src/db/__init__.py
tenbagger/src/db/create_table.py
tenbagger/src/db/read_sql.py
tenbagger/src/db/write_sql.py
tenbagger/src/dividends/__init__.py
tenbagger/src/dividends/calculator.py
tenbagger/src/dividends/div.py
tenbagger/src/financials/__init__.py
tenbagger/src/financials/revenue.py
tenbagger/src/interactive/__init__.py
tenbagger/src/interactive/candlestick.py
tenbagger/src/notify/__init__.py
tenbagger/src/notify/insider_activity.py
tenbagger/src/notify/notify_runner.py
tenbagger/src/notify/price_target.py
tenbagger/src/notify/telegramNotifier.py
tenbagger/src/passiveIncome/__init__.py
tenbagger/src/passiveIncome/calculator.py
tenbagger/src/passiveIncome/crypto.py
tenbagger/src/passiveIncome/dividends.py
tenbagger/src/portfolio/__init__.py
tenbagger/src/portfolio/core.py
tenbagger/src/portfolio/crypto.py
tenbagger/src/scripts/__init__.py
tenbagger/src/scripts/insiders.py
tenbagger/src/scripts/insiders_overview.py
tenbagger/src/scripts/sector_overview.py
tenbagger/src/scripts/tracker.py
tenbagger/src/scripts/volume.py
tenbagger/src/terminal/__init__.py
tenbagger/src/terminal/utils.py
tenbagger/src/textui/__init__.py
tenbagger/src/textui/lv.py
tenbagger/src/textui/panel.py
tenbagger/src/textui/portfolio.py
tenbagger/src/textui/utility.py
tenbagger/src/textui/apps/__init__.py
tenbagger/src/textui/apps/portfolio.py
tenbagger/src/textui/apps/ticker.py
tenbagger/src/textui/widgets/__init__.py
tenbagger/src/textui/widgets/portfolio.py
tenbagger-0.8.2.dist-info/LICENSE
tenbagger-0.8.2.dist-info/METADATA
tenbagger-0.8.2.dist-info/WHEEL
tenbagger-0.8.2.dist-info/entry_points.txt
tenbagger-0.8.2.dist-info/top_level.txt
tenbagger-0.8.2.dist-info/RECORD
