Metadata-Version: 2.1
Name: tenbagger
Version: 0.8.2
Summary: test
Home-page: https://github.com/AramKoorn/TenBagger
Author: Aram Koorn
License: UNKNOWN
Platform: UNKNOWN
License-File: LICENSE
Requires-Dist: requests (==2.26.0)
Requires-Dist: urllib3 (==1.26.6)
Requires-Dist: yfinance (==0.1.63)
Requires-Dist: pytest
Requires-Dist: pandas (==1.3.0)
Requires-Dist: numpy (==1.21.0)
Requires-Dist: matplotlib (==3.4.2)
Requires-Dist: seaborn (==0.11.1)
Requires-Dist: pyyaml (==5.4.1)
Requires-Dist: pyfiglet
Requires-Dist: yahoo-earnings-calendar
Requires-Dist: beautifulsoup4 (==4.9.3)
Requires-Dist: html5lib
Requires-Dist: plotly (==5.1.0)
Requires-Dist: dash (==1.20.0)
Requires-Dist: dash-bootstrap-components (==0.12.2)
Requires-Dist: tqdm (==4.59.0)
Requires-Dist: python-telegram-bot (==13.7)
Requires-Dist: forex-python (==1.6)
Requires-Dist: typeguard (==2.12.0)
Requires-Dist: termgraph (==0.5.1)
Requires-Dist: textual (==0.1.12)
Provides-Extra: doc
Requires-Dist: nbsphinx (>=0.8.5) ; extra == 'doc'
Requires-Dist: m2r2 ; extra == 'doc'
Requires-Dist: sphinx-rtd-theme ; extra == 'doc'
Requires-Dist: sphinx-gallery ; extra == 'doc'
Requires-Dist: readthedocs-sphinx-search ; extra == 'doc'
Provides-Extra: examples
Requires-Dist: matplotlib ; extra == 'examples'
